dapr/ext/grpc/__init__.py
dapr/ext/grpc/_health_servicer.py
dapr/ext/grpc/_servicer.py
dapr/ext/grpc/app.py
dapr/ext/grpc/version.py
dapr_ext_grpc-1.16.0.dist-info/LICENSE
dapr_ext_grpc-1.16.0.dist-info/METADATA
dapr_ext_grpc-1.16.0.dist-info/WHEEL
dapr_ext_grpc-1.16.0.dist-info/top_level.txt
dapr_ext_grpc-1.16.0.dist-info/RECORD
