Metadata-Version: 2.1
Name: dapr-ext-grpc
Version: 1.16.0
Summary: The official release of Dapr Python SDK gRPC Extension.
Home-page: https://dapr.io/
Author: Dapr Authors
Author-email: daprweb@microsoft.com
License: Apache
Project-URL: Documentation, https://github.com/dapr/docs
Project-URL: Source, https://github.com/dapr/python-sdk
Platform: UNKNOWN
Classifier: Development Status :: 5 - Production/Stable
Classifier: Intended Audience :: Developers
Classifier: License :: OSI Approved :: Apache Software License
Classifier: Operating System :: OS Independent
Classifier: Programming Language :: Python
Classifier: Programming Language :: Python :: 3.9
Classifier: Programming Language :: Python :: 3.10
Classifier: Programming Language :: Python :: 3.11
Classifier: Programming Language :: Python :: 3.12
Classifier: Programming Language :: Python :: 3.13
Requires-Python: >=3.9
License-File: LICENSE
Requires-Dist: dapr>=1.16.0
Requires-Dist: cloudevents>=1.0.0
